{"lib/images/androidstd.png":["lib/images/androidstd.png"],"lib/images/bloclogo.png":["lib/images/bloclogo.png"],"lib/images/dart.png":["lib/images/dart.png"],"lib/images/firebaselogo.png":["lib/images/firebaselogo.png"],"lib/images/flutterlogo.png":["lib/images/flutterlogo.png"],"lib/images/github.json":["lib/images/github.json"],"lib/images/github.png":["lib/images/github.png"],"lib/images/instagram.json":["lib/images/instagram.json"],"lib/images/javaimgg.png":["lib/images/javaimgg.png"],"lib/images/linkedin.json":["lib/images/linkedin.json"],"lib/images/project1.png":["lib/images/project1.png"],"lib/images/project2.png":["lib/images/project2.png"],"lib/images/resume.pdf":["lib/images/resume.pdf"],"lib/images/supabaselogo.png":["lib/images/supabaselogo.png"],"lib/images/vijayimage.png":["lib/images/vijayimage.png"],"packages/cupertino_icons/assets/CupertinoIcons.ttf":["packages/cupertino_icons/assets/CupertinoIcons.ttf"]}